{"expireTime":9007200828843514000,"key":"transformer-remark-markdown-ast-3f117b49cb7e2fc18e080ee715f609df-gatsby-remark-imagesgatsby-remark-responsive-iframegatsby-remark-prismjsgatsby-remark-copy-linked-filesgatsby-remark-smartypants-","val":{"type":"root","children":[{"type":"paragraph","children":[{"type":"text","value":"Ahora pasamos a profundizar sobre los formularios con React. Estos tienen un comportamiento diferente que en HTML, ya que podemos manejar su estado utilizando el estado de los componentes de React, haciendo más fácil el procesamiento de datos introducidos por el usuario.","position":{"start":{"line":1,"column":1,"offset":0},"end":{"line":1,"column":272,"offset":271},"indent":[]}}],"position":{"start":{"line":1,"column":1,"offset":0},"end":{"line":1,"column":272,"offset":271},"indent":[]}},{"type":"paragraph","children":[{"type":"text","value":" ","position":{"start":{"line":4,"column":1,"offset":274},"end":{"line":4,"column":7,"offset":280},"indent":[]}}],"position":{"start":{"line":4,"column":1,"offset":274},"end":{"line":4,"column":7,"offset":280},"indent":[]}},{"type":"heading","depth":2,"children":[{"type":"text","value":"Formulario simple","position":{"start":{"line":5,"column":4,"offset":284},"end":{"line":5,"column":21,"offset":301},"indent":[]}}],"position":{"start":{"line":5,"column":1,"offset":281},"end":{"line":5,"column":21,"offset":301},"indent":[]}},{"type":"paragraph","children":[{"type":"text","value":"En el siguiente ","position":{"start":{"line":7,"column":1,"offset":303},"end":{"line":7,"column":17,"offset":319},"indent":[]}},{"type":"linkReference","identifier":"ejemplo1","label":"ejemplo1","referenceType":"full","children":[{"type":"text","value":"ejemplo de formulario","position":{"start":{"line":7,"column":18,"offset":320},"end":{"line":7,"column":39,"offset":341},"indent":[]}}],"position":{"start":{"line":7,"column":17,"offset":319},"end":{"line":7,"column":50,"offset":352},"indent":[]}},{"type":"text","value":", podemos observar un formulario muy simple, el cual recoge el nombre que introducimos en el ","position":{"start":{"line":7,"column":50,"offset":352},"end":{"line":7,"column":143,"offset":445},"indent":[]}},{"type":"emphasis","children":[{"type":"text","value":"input","position":{"start":{"line":7,"column":144,"offset":446},"end":{"line":7,"column":149,"offset":451},"indent":[]}}],"position":{"start":{"line":7,"column":143,"offset":445},"end":{"line":7,"column":150,"offset":452},"indent":[]}},{"type":"text","value":".","position":{"start":{"line":7,"column":150,"offset":452},"end":{"line":7,"column":151,"offset":453},"indent":[]}}],"position":{"start":{"line":7,"column":1,"offset":303},"end":{"line":7,"column":151,"offset":453},"indent":[]}},{"type":"paragraph","children":[{"type":"text","value":" ","position":{"start":{"line":10,"column":1,"offset":456},"end":{"line":10,"column":7,"offset":462},"indent":[]}}],"position":{"start":{"line":10,"column":1,"offset":456},"end":{"line":10,"column":7,"offset":462},"indent":[]}},{"type":"heading","depth":3,"children":[{"type":"text","value":"Componentes controlados","position":{"start":{"line":11,"column":5,"offset":467},"end":{"line":11,"column":28,"offset":490},"indent":[]}}],"position":{"start":{"line":11,"column":1,"offset":463},"end":{"line":11,"column":28,"offset":490},"indent":[]}},{"type":"paragraph","children":[{"type":"text","value":"Ahora vayamos un paso más allá. Por ejemplo, queremos que los datos introducidos actualicen el estado del nodo cada vez que sufren un cambio (mientras el usuario introduce los datos, por ejemplo). Para ello, utilizaremos el siguiente ","position":{"start":{"line":13,"column":1,"offset":492},"end":{"line":13,"column":235,"offset":726},"indent":[]}},{"type":"linkReference","identifier":"ejemplo2","label":"ejemplo2","referenceType":"full","children":[{"type":"text","value":"ejemplo","position":{"start":{"line":13,"column":236,"offset":727},"end":{"line":13,"column":243,"offset":734},"indent":[]}}],"position":{"start":{"line":13,"column":235,"offset":726},"end":{"line":13,"column":254,"offset":745},"indent":[]}},{"type":"text","value":". Podemos observar que cada vez que introducimos datos, el componente lo muestra en mayúscula, por lo que actualiza el contenido del campo ‘name’, y posteriormente, una vez que pulsamos el botón de ‘Enviar’, se muestra una alerta por pantalla.","position":{"start":{"line":13,"column":254,"offset":745},"end":{"line":13,"column":497,"offset":988},"indent":[]}}],"position":{"start":{"line":13,"column":1,"offset":492},"end":{"line":13,"column":497,"offset":988},"indent":[]}},{"type":"paragraph","children":[{"type":"text","value":"Este elemento del formulario creado se conoce como ","position":{"start":{"line":15,"column":1,"offset":990},"end":{"line":15,"column":52,"offset":1041},"indent":[]}},{"type":"strong","children":[{"type":"text","value":"componente controlado","position":{"start":{"line":15,"column":54,"offset":1043},"end":{"line":15,"column":75,"offset":1064},"indent":[]}}],"position":{"start":{"line":15,"column":52,"offset":1041},"end":{"line":15,"column":77,"offset":1066},"indent":[]}},{"type":"text","value":" ya que tiene enlazado su ","position":{"start":{"line":15,"column":77,"offset":1066},"end":{"line":15,"column":103,"offset":1092},"indent":[]}},{"type":"emphasis","children":[{"type":"text","value":"value","position":{"start":{"line":15,"column":104,"offset":1093},"end":{"line":15,"column":109,"offset":1098},"indent":[]}}],"position":{"start":{"line":15,"column":103,"offset":1092},"end":{"line":15,"column":110,"offset":1099},"indent":[]}},{"type":"text","value":" con el estado del componente. Esto permite, por ejemplo, realizar comprobaciones o validaciones mientras el usuario introduce datos, y a su vez, reflejarlo en el input, en este caso, cambiandolo a mayuscula.","position":{"start":{"line":15,"column":110,"offset":1099},"end":{"line":15,"column":318,"offset":1307},"indent":[]}}],"position":{"start":{"line":15,"column":1,"offset":990},"end":{"line":15,"column":318,"offset":1307},"indent":[]}},{"type":"paragraph","children":[{"type":"text","value":" ","position":{"start":{"line":18,"column":1,"offset":1310},"end":{"line":18,"column":7,"offset":1316},"indent":[]}}],"position":{"start":{"line":18,"column":1,"offset":1310},"end":{"line":18,"column":7,"offset":1316},"indent":[]}},{"type":"heading","depth":3,"children":[{"type":"text","value":"Componentes no controlados: ","position":{"start":{"line":19,"column":5,"offset":1321},"end":{"line":19,"column":33,"offset":1349},"indent":[]}},{"type":"emphasis","children":[{"type":"text","value":"file","position":{"start":{"line":19,"column":34,"offset":1350},"end":{"line":19,"column":38,"offset":1354},"indent":[]}}],"position":{"start":{"line":19,"column":33,"offset":1349},"end":{"line":19,"column":39,"offset":1355},"indent":[]}}],"position":{"start":{"line":19,"column":1,"offset":1317},"end":{"line":19,"column":39,"offset":1355},"indent":[]}},{"type":"paragraph","children":[{"type":"text","value":"Hasta ahora hemos visto que podemos manejar cualquier elemento de un formulario, pero existe una excepción, el campo de tipo fichero ","position":{"start":{"line":21,"column":1,"offset":1357},"end":{"line":21,"column":134,"offset":1490},"indent":[]}},{"type":"emphasis","children":[{"type":"text","value":"file","position":{"start":{"line":21,"column":135,"offset":1491},"end":{"line":21,"column":139,"offset":1495},"indent":[]}}],"position":{"start":{"line":21,"column":134,"offset":1490},"end":{"line":21,"column":140,"offset":1496},"indent":[]}},{"type":"text","value":". Este campo no puede ser controlado por temas de seguridad.","position":{"start":{"line":21,"column":140,"offset":1496},"end":{"line":21,"column":200,"offset":1556},"indent":[]}}],"position":{"start":{"line":21,"column":1,"offset":1357},"end":{"line":21,"column":200,"offset":1556},"indent":[]}},{"type":"paragraph","children":[{"type":"text","value":"Por ello, se debe acceder a él mediante una referencia al DOM gestionada por React, como se especifica en el siguiente ","position":{"start":{"line":23,"column":1,"offset":1558},"end":{"line":23,"column":120,"offset":1677},"indent":[]}},{"type":"linkReference","identifier":"ejemplo3","label":"ejemplo3","referenceType":"full","children":[{"type":"text","value":"ejemplo","position":{"start":{"line":23,"column":121,"offset":1678},"end":{"line":23,"column":128,"offset":1685},"indent":[]}}],"position":{"start":{"line":23,"column":120,"offset":1677},"end":{"line":23,"column":139,"offset":1696},"indent":[]}}],"position":{"start":{"line":23,"column":1,"offset":1558},"end":{"line":23,"column":139,"offset":1696},"indent":[]}},{"type":"definition","identifier":"ejemplo1","label":"ejemplo1","title":null,"url":"https://codepen.io/Javier_Herrero/pen/OJJQLgg?editors=0010","position":{"start":{"line":25,"column":1,"offset":1698},"end":{"line":25,"column":70,"offset":1767},"indent":[]}},{"type":"definition","identifier":"ejemplo2","label":"ejemplo2","title":null,"url":"https://codepen.io/Javier_Herrero/pen/bGGLbML?editors=0010","position":{"start":{"line":26,"column":1,"offset":1768},"end":{"line":26,"column":71,"offset":1838},"indent":[]}},{"type":"definition","identifier":"ejemplo3","label":"ejemplo3","title":null,"url":"https://codepen.io/Javier_Herrero/pen/PooQYyJ","position":{"start":{"line":27,"column":1,"offset":1839},"end":{"line":27,"column":58,"offset":1896},"indent":[]}}],"position":{"start":{"line":1,"column":1,"offset":0},"end":{"line":27,"column":58,"offset":1896}}}}